badges_io/__init__.py
badges_io/__main__.py
badges_io/badges.py
badges_io/slug.py
badges_io-1.0.8.dist-info/LICENSE
badges_io-1.0.8.dist-info/METADATA
badges_io-1.0.8.dist-info/WHEEL
badges_io-1.0.8.dist-info/top_level.txt
badges_io-1.0.8.dist-info/RECORD
