Metadata-Version: 2.1
Name: badges-io
Version: 1.0.8
Summary: Uploads total coverage for displaying badge
Home-page: https://github.com/Volumental/badges
Author: Samuel Carlsson
Author-email: samuel.carlsson@volumental.com
License: UNKNOWN
Keywords: badge,shield,shields.io
Platform: UNKNOWN
